CHANGELOG.md
README.md
speedy_openai/__init__.py
speedy_openai/client.py
speedy_openai/configs.py
speedy_openai/rate_limiter.py
speedy_openai-0.3.0.dist-info/LICENSE
speedy_openai-0.3.0.dist-info/METADATA
speedy_openai-0.3.0.dist-info/WHEEL
speedy_openai-0.3.0.dist-info/RECORD
