Metadata-Version: 2.1
Name: speedy-openai
Version: 0.3.0
Summary: Async OpenAI client for fast and efficient API requests using AIOHTTP module.
Home-page: https://github.com/lucafirefox/speedy-openai
License: MIT
Keywords: openai,async,aiohttp,api
Author: Luca Ferrario
Author-email: lucaferrario199@gmail.com
Requires-Python: >=3.9,<3.13
Classifier: Intended Audience :: Developers
Classifier: License :: OSI Approved :: MIT License
Classifier: Operating System :: OS Independent
Classifier: Programming Language :: Python
Classifier: Programming Language :: Python :: 3
Classifier: Programming Language :: Python :: 3.9
Classifier: Programming Language :: Python :: 3.10
Classifier: Programming Language :: Python :: 3.11
Classifier: Programming Language :: Python :: 3.12
Classifier: Topic :: Software Development :: Libraries :: Python Modules
Requires-Dist: aiohttp (>=3.11.10,<4.0.0)
Requires-Dist: loguru (>=0.7.3,<0.8.0)
Requires-Dist: openai (>=1.57.4,<2.0.0)
Requires-Dist: tenacity (>=9.0.0,<10.0.0)
Requires-Dist: tiktoken (>=0.11.0,<0.12.0)
Requires-Dist: tqdm (>=4.67.1,<5.0.0)
Project-URL: Documentation, https://github.com/lucafirefox/speedy-openai#readme
Project-URL: Repository, https://github.com/lucafirefox/speedy-openai
